knotification/__init__.py
knotification/__main__.py
knotification/sample.py
knotification/image/error.png
knotification/image/info.png
knotification/sound/error.wav
knotification/sound/error2.aiff
knotification/sound/notification.wav
knotification/src/__init__.py
knotification/src/knotification.py
knotification-0.1.0.7.dist-info/METADATA
knotification-0.1.0.7.dist-info/WHEEL
knotification-0.1.0.7.dist-info/top_level.txt
knotification-0.1.0.7.dist-info/RECORD
